kiwitcms_github_marketplace-4.2.8.dist-info/licenses/LICENSE
tcms_github_marketplace/__init__.py
tcms_github_marketplace/admin.py
tcms_github_marketplace/api.py
tcms_github_marketplace/apps.py
tcms_github_marketplace/checks.py
tcms_github_marketplace/cron_github_recurring_billing.py
tcms_github_marketplace/docker.py
tcms_github_marketplace/fastspring.py
tcms_github_marketplace/forms.py
tcms_github_marketplace/github.py
tcms_github_marketplace/mailchimp.py
tcms_github_marketplace/menu.py
tcms_github_marketplace/models.py
tcms_github_marketplace/urls.py
tcms_github_marketplace/utils.py
tcms_github_marketplace/views.py
tcms_github_marketplace/migrations/0001_initial.py
tcms_github_marketplace/migrations/0002_update_fields.py
tcms_github_marketplace/migrations/0003_sender_email_field.py
tcms_github_marketplace/migrations/0004_models_jsonfield.py
tcms_github_marketplace/migrations/0005_add_support_and_tenant_flags.py
tcms_github_marketplace/migrations/0006_add_subscription_field.py
tcms_github_marketplace/migrations/0007_manualpurchase.py
tcms_github_marketplace/migrations/0008_add_gitops_prefix.py
tcms_github_marketplace/migrations/0009_github_subscription_id.py
tcms_github_marketplace/migrations/0010_prefix_fastspring_subscription_id.py
tcms_github_marketplace/migrations/0011_quay_accounts.py
tcms_github_marketplace/migrations/__init__.py
tcms_github_marketplace/quay/LICENSE
tcms_github_marketplace/quay/README.rst
tcms_github_marketplace/quay/__init__.py
tcms_github_marketplace/quay/quay_api_client.py
tcms_github_marketplace/quay/quay_session.py
tcms_github_marketplace/static/tcms_github_marketplace/js/subscription.js
tcms_github_marketplace/templates/email/manual_subscription_notification.txt
tcms_github_marketplace/templates/tcms_github_marketplace/subscription.html
tcms_github_marketplace/templates/tcms_github_marketplace/email/exit_poll.txt
tcms_github_marketplace/templates/tcms_tenants/override_edit.html
tcms_github_marketplace/templates/tcms_tenants/override_new.html
kiwitcms_github_marketplace-4.2.8.dist-info/METADATA
kiwitcms_github_marketplace-4.2.8.dist-info/WHEEL
kiwitcms_github_marketplace-4.2.8.dist-info/entry_points.txt
kiwitcms_github_marketplace-4.2.8.dist-info/top_level.txt
kiwitcms_github_marketplace-4.2.8.dist-info/RECORD
