Metadata-Version: 2.4
Name: kiwitcms-github-marketplace
Version: 4.2.8
Summary: GitHub Marketplace integration for Kiwi TCMS
Home-page: https://github.com/kiwitcms/github-marketplace/
Author: Kiwi TCMS
Author-email: info@kiwitcms.org
License: AGPLv3+
Classifier: Framework :: Django
Classifier: Development Status :: 5 - Production/Stable
Classifier: Topic :: Software Development :: Quality Assurance
Classifier: Topic :: Software Development :: Testing
Classifier: Environment :: Web Environment
Classifier: Intended Audience :: Developers
Classifier: License :: OSI Approved :: GNU Affero General Public License v3 or later (AGPLv3+)
Classifier: Programming Language :: Python :: 3
Classifier: Programming Language :: Python :: 3.8
Classifier: Programming Language :: Python :: 3.9
Classifier: Programming Language :: Python :: 3.11
License-File: LICENSE
Requires-Dist: kiwitcms-tenants>=2.8.3
Requires-Dist: mailchimp3==3.0.21
Requires-Dist: requests
Requires-Dist: sqlparse>=0.5.0
Requires-Dist: urllib3>=2.2.2
Dynamic: author
Dynamic: author-email
Dynamic: classifier
Dynamic: description
Dynamic: home-page
Dynamic: license
Dynamic: license-file
Dynamic: requires-dist
Dynamic: summary
